ldr/logging/__init__.py
ldr/logging/models.py
ldr/logging/setup.py
ldr_logging-0.1.1.dist-info/LICENSE.md
ldr_logging-0.1.1.dist-info/METADATA
ldr_logging-0.1.1.dist-info/WHEEL
ldr_logging-0.1.1.dist-info/RECORD
